fredcollect/__init__.py
fredcollect/build_request.py
fredcollect/fred.py
fredcollect/parameters.py
fredcollect/request_types.py
fredcollect/run.py
fredcollect/utils.py
fredcollect/clean/__init__.py
fredcollect/clean/categories.py
fredcollect/clean/releases.py
fredcollect/clean/series.py
fredcollect/clean/sources.py
fredcollect/clean/tags.py
fredcollect-0.1.2.dist-info/licenses/LICENSE
fredcollect-0.1.2.dist-info/METADATA
fredcollect-0.1.2.dist-info/WHEEL
fredcollect-0.1.2.dist-info/top_level.txt
fredcollect-0.1.2.dist-info/RECORD
