Metadata-Version: 2.4
Name: fredcollect
Version: 0.1.2
Summary: A Python wrapper for the Federal Reserve Economic Database (FRED) API
Home-page: https://github.com/versaucc/fredcollect
Author: Oliver Grenon
Author-email: Oliver Grenon <grenonoliver@gmail.com>
License: Apache-2.0
Project-URL: Homepage, https://github.com/versaucc/fredcollect
Project-URL: Repository, https://github.com/versaucc/fredcollect
Project-URL: Issues, https://github.com/versaucc/fredcollect/issues
Keywords: FRED,Federal Reserve,Economic Data,API,Economics
Classifier: Development Status :: 4 - Beta
Classifier: Intended Audience :: Developers
Classifier: Intended Audience :: Financial and Insurance Industry
Classifier: Intended Audience :: Science/Research
Classifier: License :: OSI Approved :: Apache Software License
Classifier: Operating System :: OS Independent
Classifier: Programming Language :: Python :: 3
Classifier: Programming Language :: Python :: 3.7
Classifier: Programming Language :: Python :: 3.8
Classifier: Programming Language :: Python :: 3.9
Classifier: Programming Language :: Python :: 3.10
Classifier: Programming Language :: Python :: 3.11
Classifier: Topic :: Office/Business :: Financial
Classifier: Topic :: Scientific/Engineering :: Information Analysis
Requires-Python: >=3.7
License-File: LICENSE
Requires-Dist: requests
Requires-Dist: pandas>=1.5.3
Requires-Dist: numpy>=1.23.5
Requires-Dist: python-dotenv
Requires-Dist: matplotlib
Provides-Extra: dev
Requires-Dist: pytest; extra == "dev"
Requires-Dist: black; extra == "dev"
Requires-Dist: flake8; extra == "dev"
Requires-Dist: mypy; extra == "dev"
Requires-Dist: isort; extra == "dev"
Dynamic: author
Dynamic: home-page
Dynamic: license-file
Dynamic: requires-python
